wasend/__init__.py
wasend/py.typed
wasend/_jsii/__init__.py
wasend/_jsii/core@1.3.3.jsii.tgz
wasend-1.3.3.dist-info/LICENSE
wasend-1.3.3.dist-info/METADATA
wasend-1.3.3.dist-info/WHEEL
wasend-1.3.3.dist-info/top_level.txt
wasend-1.3.3.dist-info/RECORD
